cairn/__init__.py
cairn/cli.py
cairn/versions.py
cairn-0.2.3.dist-info/LICENSE
cairn-0.2.3.dist-info/METADATA
cairn-0.2.3.dist-info/WHEEL
cairn-0.2.3.dist-info/entry_points.txt
cairn-0.2.3.dist-info/top_level.txt
cairn-0.2.3.dist-info/RECORD
