Metadata-Version: 2.1
Name: cairn
Version: 0.2.3
Summary: Tools and utilities for managing project versions
Home-page: https://github.com/ejfitzgerald/cairn/
Author: Ed FitzGerald
Author-email: edward.fitzgerald@fetch.ai
License: UNKNOWN
Platform: UNKNOWN
Provides-Extra: dev
Requires-Dist: check-manifest ; extra == 'dev'
Provides-Extra: test
Requires-Dist: coverage ; extra == 'test'
Requires-Dist: pytest ; extra == 'test'
Requires-Dist: tox ; extra == 'test'
